<layer>
  <name>layer_structure_geo</name>
  <id>LayerInfoImpl--bb68920:19f114781fa:-7f1b</id>
  <type>VECTOR</type>
  <defaultStyle>
    <id>StyleInfoImpl--bb68920:19f114781fa:-7f16</id>
  </defaultStyle>
  <resource class="featureType">
    <id>FeatureTypeInfoImpl--bb68920:19f114781fa:-7f1c</id>
  </resource>
  <queryable>true</queryable>
  <opaque>false</opaque>
  <attribution>
    <logoWidth>0</logoWidth>
    <logoHeight>0</logoHeight>
  </attribution>
  <dateCreated>2026-06-29 03:31:30.176 UTC</dateCreated>
  <dateModified>2026-06-29 09:50:06.760 UTC</dateModified>
</layer>